{
	"combat": {
		"attack_disengage_count": 0,
		"attack_max_continuous": 11.9166666666667,
		"damage_by_weapon": {
			"assault_rifle": 90.0,
			"pistol": 850.0,
			"railgun": 50.0,
			"shotgun": 72.0
		},
		"kill_distances": {

		},
		"kills_by_weapon": {
			"assault_rifle": 0,
			"pistol": 0,
			"railgun": 0,
			"shotgun": 0
		},
		"shots_fired": 116,
		"total_damage_dealt": 1062.0
	},
	"core": {
		"deaths_by_stage": {
			"1": 3,
			"2": 6,
			"3": 2
		},
		"duration": 84.81,
		"heals_by_stage": {
			"1": 1,
			"2": 9,
			"3": 2
		},
		"zone_stage_reached": 3
	},
	"economy": {
		"first_upgrade_time": 7.938,
		"first_upgrade_weapon": "shotgun",
		"heals_used": 12,
		"rare_pickups": 28,
		"shields_picked": 0,
		"weapon_pickups": {
			"assault_rifle": 5,
			"pistol": 9,
			"railgun": 2,
			"shotgun": 8
		}
	},
	"enabled_groups": {
		"combat": true,
		"core": true,
		"economy": true,
		"supply": true,
		"tactics": true,
		"zone": true
	},
	"session": {
		"assists": 0,
		"kills": 0,
		"rank": 1,
		"win": true
	},
	"supply": {
		"contests": 5,
		"preannounce_interest": 1,
		"telegraphed": true,
		"visits": 0
	},
	"tactics": {
		"ammo_empty_enter": 0,
		"died_in_recover": 0,
		"disengage_triggered": 27,
		"patrol_entered": 0,
		"patrol_timeout": 0,
		"recover_bouts": 3,
		"recover_success": 9,
		"reserve_reload": 0,
		"stuck_triggered": 14,
		"weapon_drop_spawned": 10
	},
	"zone": {
		"final_duel_deaths": [
			{
				"bot_hp": -10.0,
				"cause": "gun",
				"outside_sec": 0.0,
				"stage": 3,
				"state": "RECOVER",
				"stuck_sec": 0.0,
				"was_stuck": false,
				"zone_dist_ratio": 0.26
			}
		],
		"max_outside_time": 0.0,
		"zone_deaths": 0,
		"zone_deaths_by_state": {

		}
	}
}